simplecalculator_kj/__init__.py
simplecalculator_kj/cli.py
simplecalculator_kj-0.0.2.dist-info/METADATA
simplecalculator_kj-0.0.2.dist-info/WHEEL
simplecalculator_kj-0.0.2.dist-info/entry_points.txt
simplecalculator_kj-0.0.2.dist-info/licenses/LICENSE
simplecalculator_kj-0.0.2.dist-info/RECORD
