Metadata-Version: 2.4
Name: simplecalculator-kj
Version: 0.0.2
Summary: Short description
Author-email: Kasper Jørgensen <you@example.com>
License-File: LICENSE
Requires-Python: >=3.9
Requires-Dist: numpy>=1.26
